firetail/__init__.py
firetail/__main__.py
firetail/auditor.py
firetail/cli.py
firetail/exceptions.py
firetail/flusher.py
firetail/handlers.py
firetail/http_facts.py
firetail/json_schema.py
firetail/jsonifier.py
firetail/lifecycle.py
firetail/logger.py
firetail/mock.py
firetail/options.py
firetail/problem.py
firetail/resolver.py
firetail/sender.py
firetail/spec.py
firetail/utils.py
firetail/apis/__init__.py
firetail/apis/abstract.py
firetail/apis/aiohttp_api.py
firetail/apis/flask_api.py
firetail/apis/flask_utils.py
firetail/apps/__init__.py
firetail/apps/abstract.py
firetail/apps/aiohttp_app.py
firetail/apps/flask_app.py
firetail/decorators/__init__.py
firetail/decorators/coroutine_wrappers.py
firetail/decorators/decorator.py
firetail/decorators/metrics.py
firetail/decorators/parameter.py
firetail/decorators/produces.py
firetail/decorators/response.py
firetail/decorators/uri_parsing.py
firetail/decorators/validation.py
firetail/middleware/__init__.py
firetail/middleware/base.py
firetail/middleware/main.py
firetail/middleware/swagger_ui.py
firetail/operations/__init__.py
firetail/operations/abstract.py
firetail/operations/compat.py
firetail/operations/openapi.py
firetail/operations/secure.py
firetail/operations/swagger2.py
firetail/resources/schemas/v2.0/schema.json
firetail/resources/schemas/v3.0/schema.json
firetail/security/__init__.py
firetail/security/aiohttp_security_handler_factory.py
firetail/security/async_security_handler_factory.py
firetail/security/flask_security_handler_factory.py
firetail/security/security_handler_factory.py
firetail-1.1.1.dist-info/LICENSE.txt
firetail-1.1.1.dist-info/METADATA
firetail-1.1.1.dist-info/WHEEL
firetail-1.1.1.dist-info/entry_points.txt
firetail-1.1.1.dist-info/top_level.txt
firetail-1.1.1.dist-info/RECORD
