Metadata-Version: 2.1
Name: firetail
Version: 1.1.1
Summary: Firetail - API first applications with OpenAPI/Swagger and Flask
Home-page: https://github.com/FireTail-io/firetail-py-lib
Author: FireTail International (TM)
License: LGPLv3
Keywords: openapi oai swagger rest api oauth flask microservice framework
Platform: UNKNOWN
Classifier: Programming Language :: Python
Classifier: Programming Language :: Python :: 3.7
Classifier: Programming Language :: Python :: 3.8
Classifier: Programming Language :: Python :: 3.9
Classifier: Programming Language :: Python :: 3.10
Classifier: Development Status :: 5 - Production/Stable
Classifier: Intended Audience :: Developers
Classifier: Operating System :: OS Independent
Classifier: Topic :: Internet :: WWW/HTTP :: WSGI :: Application
Classifier: Topic :: Software Development :: Libraries :: Application Frameworks
Requires-Python: >=3.6
License-File: LICENSE.txt
Requires-Dist: clickclick<21,>=1.2
Requires-Dist: jsonschema<5,>=4.0.1
Requires-Dist: PyYAML<7,>=6.0.1
Requires-Dist: PyJWT>=2.4.0
Requires-Dist: requests<3,>=2.31
Requires-Dist: inflection<0.6,>=0.3.1
Requires-Dist: werkzeug<3,>=2.2.2
Requires-Dist: starlette<1,>=0.27
Requires-Dist: packaging>=23.2
Requires-Dist: flask[async]==2.2.5
Requires-Dist: a2wsgi<2,>=1.4
Provides-Extra: docs
Requires-Dist: sphinx-autoapi==1.8.1; extra == "docs"
Provides-Extra: flask
Requires-Dist: flask[async]==2.2.5; extra == "flask"
Requires-Dist: a2wsgi<2,>=1.4; extra == "flask"
Provides-Extra: swagger-ui
Requires-Dist: swagger-ui-bundle<0.1,>=0.0.2; extra == "swagger-ui"
Provides-Extra: tests
Requires-Dist: pytest<7,>=6; extra == "tests"
Requires-Dist: pytest-cov<3,>=2; extra == "tests"
Requires-Dist: testfixtures<7,>=6; extra == "tests"
Requires-Dist: flask[async]==2.2.5; extra == "tests"
Requires-Dist: a2wsgi<2,>=1.4; extra == "tests"
Requires-Dist: swagger-ui-bundle<0.1,>=0.0.2; extra == "tests"
Requires-Dist: aiohttp<4,>=2.3.10; extra == "tests"
Requires-Dist: aiohttp-jinja2<2,>=0.14.0; extra == "tests"
Requires-Dist: MarkupSafe>=0.23; extra == "tests"
Requires-Dist: pytest-aiohttp; extra == "tests"
Requires-Dist: aiohttp-remotes; extra == "tests"
